api/__init__.py
api/index.py
api/namefinder.py
fling_api-0.1.3.dist-info/METADATA
fling_api-0.1.3.dist-info/WHEEL
fling_api-0.1.3.dist-info/RECORD
