Metadata-Version: 2.1
Name: fling-api
Version: 0.1.3
Summary: Side Project Management API for Data Storage and Name Searches
Author: Joshua McKenty
Author-email: jmckenty@gmail.com
Requires-Python: >=3.9,<4.0
Classifier: Programming Language :: Python :: 3
Classifier: Programming Language :: Python :: 3.9
Classifier: Programming Language :: Python :: 3.10
Classifier: Programming Language :: Python :: 3.11
Requires-Dist: boto3 (>=1.26.108,<2.0.0)
Requires-Dist: cachetools (>=5.3.0,<6.0.0)
Requires-Dist: fastapi (>=0.95.0,<0.96.0)
Requires-Dist: fling-core (>=0.1.3,<0.2.0)
Requires-Dist: openai (>=0.27.4,<0.28.0)
Requires-Dist: python-dotenv (>=1.0.0,<2.0.0)
Requires-Dist: uvicorn (>=0.21.1,<0.22.0)
